pdc_struct/__init__.py
pdc_struct/c_types.py
pdc_struct/enums.py
pdc_struct/exc.py
pdc_struct/types.py
pdc_struct/utils.py
pdc_struct/models/__init__.py
pdc_struct/models/bit_field.py
pdc_struct/models/struct_config.py
pdc_struct/models/struct_model.py
pdc_struct/models/structmodel_handler.py
pdc_struct/type_handler/__init__.py
pdc_struct/type_handler/bit_field.py
pdc_struct/type_handler/bool_handler.py
pdc_struct/type_handler/bytes_handler.py
pdc_struct/type_handler/enum_handler.py
pdc_struct/type_handler/float_handler.py
pdc_struct/type_handler/int_handler.py
pdc_struct/type_handler/ipaddr_handler.py
pdc_struct/type_handler/meta.py
pdc_struct/type_handler/string_handler.py
pdc_struct/type_handler/uuid_handler.py
pdc_struct-1.0.0.dist-info/METADATA
pdc_struct-1.0.0.dist-info/WHEEL
pdc_struct-1.0.0.dist-info/licenses/LICENSE
pdc_struct-1.0.0.dist-info/RECORD
