Metadata-Version: 2.4
Name: pdc-struct
Version: 1.0.0
Summary: A Pydantic extension for struct-compatible serialization
Project-URL: Homepage, https://github.com/boxcake/pdc_struct
Project-URL: Documentation, https://boxcake.github.io/pdc_struct
Project-URL: Bug Tracker, https://github.com/boxcake/pdc_struct/issues
Project-URL: Repository, https://github.com/boxcake/pdc_struct
Author-email: Jonathan Baker <jon@boxcake.net>
License-File: LICENSE
Keywords: binary,bytes,c-interop,networking,pack,pydantic,serialization,struct,unpack
Classifier: Development Status :: 4 - Beta
Classifier: Intended Audience :: Developers
Classifier: License :: OSI Approved :: MIT License
Classifier: Operating System :: OS Independent
Classifier: Programming Language :: Python :: 3
Classifier: Programming Language :: Python :: 3.11
Classifier: Programming Language :: Python :: 3.12
Classifier: Programming Language :: Python :: 3.13
Classifier: Topic :: Software Development :: Code Generators
Classifier: Topic :: Software Development :: Libraries :: Python Modules
Classifier: Topic :: System :: Networking
Requires-Python: >=3.11
Requires-Dist: pydantic>=2.0.0
Provides-Extra: dev
Requires-Dist: black>=23.0; extra == 'dev'
Requires-Dist: mkdocs-material>=9.0; extra == 'dev'
Requires-Dist: mkdocstrings[python]>=0.24; extra == 'dev'
Requires-Dist: pytest-cov>=4.0; extra == 'dev'
Requires-Dist: pytest>=7.0; extra == 'dev'
Requires-Dist: ruff>=0.1.0; extra == 'dev'
Provides-Extra: docs
Requires-Dist: mkdocs-git-revision-date-localized-plugin>=1.2; extra == 'docs'
Requires-Dist: mkdocs-material>=9.0; extra == 'docs'
Requires-Dist: mkdocstrings[python]>=0.24; extra == 'docs'
Provides-Extra: security
Requires-Dist: bandit>=1.7; extra == 'security'
Requires-Dist: pip-audit>=2.6; extra == 'security'
Provides-Extra: test
Requires-Dist: pytest-cov>=4.0; extra == 'test'
Requires-Dist: pytest>=7.0; extra == 'test'
